[
null,
{"id":1,"animationId":6,"description":"[Sword] A light and easy-to-wield short-bladed sword.","etypeId":1,"traits":[{"code":31,"dataId":1,"value":0},{"code":22,"dataId":0,"value":0}],"iconIndex":97,"name":"Short Sword","note":"","params":[0,0,8,0,0,0,0,0],"price":300,"wtypeId":2},
{"id":2,"animationId":6,"description":"[Sword] A long battle sword boasting a sharp cut.","etypeId":1,"traits":[{"code":31,"dataId":1,"value":0},{"code":22,"dataId":0,"value":0}],"iconIndex":97,"name":"Long Sword","note":"","params":[0,0,12,0,0,0,0,0],"price":670,"wtypeId":2},
{"id":3,"animationId":6,"description":"[Sword] A wide sword with a curved blade.","etypeId":1,"traits":[{"code":31,"dataId":1,"value":0},{"code":22,"dataId":0,"value":0}],"iconIndex":97,"name":"Falchion","note":"","params":[0,0,18,0,0,0,0,0],"price":1480,"wtypeId":2},
{"id":4,"animationId":6,"description":"[Sword] A long sword forged with mithril.","etypeId":1,"traits":[{"code":31,"dataId":1,"value":0},{"code":22,"dataId":0,"value":0}],"iconIndex":97,"name":"Mithril Sword","note":"","params":[0,0,25,0,0,0,0,0],"price":3890,"wtypeId":2},
{"id":5,"animationId":6,"description":"[Sword] A sword forged from the fangs of a dragon.","etypeId":1,"traits":[{"code":31,"dataId":1,"value":0},{"code":22,"dataId":0,"value":0}],"iconIndex":97,"name":"Dragon Blade","note":"","params":[0,0,36,0,0,0,0,0],"price":6970,"wtypeId":2},
{"id":6,"animationId":0,"description":"","etypeId":1,"traits":[{"code":31,"dataId":1,"value":0},{"code":22,"dataId":0,"value":0}],"iconIndex":0,"name":"","note":"","params":[0,0,0,0,0,0,0,0],"price":0,"wtypeId":0},
{"id":7,"animationId":1,"description":"[Staff] An inexpensive and widely-used staff.","etypeId":1,"traits":[{"code":31,"dataId":1,"value":0},{"code":22,"dataId":0,"value":0}],"iconIndex":101,"name":"Wooden Staff","note":"","params":[0,0,2,0,8,3,0,0],"price":280,"wtypeId":6},
{"id":8,"animationId":1,"description":"[Staff] A wand that slightly increases its wielder’s\nmagical powers.","etypeId":1,"traits":[{"code":31,"dataId":1,"value":0},{"code":22,"dataId":0,"value":0}],"iconIndex":101,"name":"Magic Wand","note":"","params":[0,0,3,0,12,6,0,0],"price":780,"wtypeId":6},
{"id":9,"animationId":1,"description":"[Staff] A silver wand that increases its wielder’s\nmagical powers.","etypeId":1,"traits":[{"code":31,"dataId":1,"value":0},{"code":22,"dataId":0,"value":0}],"iconIndex":101,"name":"Force Wand","note":"","params":[0,0,5,0,21,12,0,0],"price":1680,"wtypeId":6},
{"id":10,"animationId":1,"description":"[Staff] A mithril rod that increases its wielder’s\nmagical powers.","etypeId":1,"traits":[{"code":31,"dataId":1,"value":0},{"code":22,"dataId":0,"value":0}],"iconIndex":101,"name":"Mithril Rod","note":"","params":[0,0,12,0,32,24,0,0],"price":4120,"wtypeId":6},
{"id":11,"animationId":1,"description":"[Staff] A dragon staff that increases its wielder’s\nmagical powers.","etypeId":1,"traits":[{"code":31,"dataId":1,"value":0},{"code":22,"dataId":0,"value":0}],"iconIndex":101,"name":"Dragon Staff","note":"","params":[0,0,18,0,45,52,0,0],"price":7680,"wtypeId":6},
{"id":12,"animationId":0,"description":"","etypeId":1,"traits":[{"code":31,"dataId":1,"value":0},{"code":22,"dataId":0,"value":0}],"iconIndex":0,"name":"","note":"","params":[0,0,0,0,0,0,0,0],"price":0,"wtypeId":0},
{"id":13,"animationId":1,"description":"[Flail] A flail with a stone head attached to its\nhandle with a chain.","etypeId":1,"traits":[{"code":31,"dataId":1,"value":0},{"code":22,"dataId":0,"value":0}],"iconIndex":98,"name":"Stone Flail","note":"","params":[0,0,7,0,0,0,0,0],"price":360,"wtypeId":3},
{"id":14,"animationId":1,"description":"[Flail] A flail with a bronze head attached to its\nhandle with a chain.","etypeId":1,"traits":[{"code":31,"dataId":1,"value":0},{"code":22,"dataId":0,"value":0}],"iconIndex":98,"name":"Bronze Flail","note":"","params":[0,0,12,0,0,0,0,0],"price":680,"wtypeId":3},
{"id":15,"animationId":1,"description":"[Flail] A flail that has been strengthened with steel.","etypeId":1,"traits":[{"code":31,"dataId":1,"value":0},{"code":22,"dataId":0,"value":0}],"iconIndex":98,"name":"Morning Star","note":"","params":[0,0,18,0,0,0,0,0],"price":1460,"wtypeId":3},
{"id":16,"animationId":1,"description":"[Flail] A flail that has been strengthened with mithril.","etypeId":1,"traits":[{"code":31,"dataId":1,"value":0},{"code":22,"dataId":0,"value":0}],"iconIndex":98,"name":"Mithril Flail","note":"","params":[0,0,23,0,0,0,0,0],"price":2980,"wtypeId":3},
{"id":17,"animationId":1,"description":"[Flail] A flail that has been strengthened using fangs of a dragon.","etypeId":1,"traits":[{"code":31,"dataId":1,"value":0},{"code":22,"dataId":0,"value":0}],"iconIndex":98,"name":"Dragon Flail","note":"","params":[0,0,29,0,0,0,0,0],"price":6180,"wtypeId":3},
{"id":18,"animationId":0,"description":"","etypeId":1,"traits":[{"code":31,"dataId":1,"value":0},{"code":22,"dataId":0,"value":0}],"iconIndex":0,"name":"","note":"","params":[0,0,0,0,0,0,0,0],"price":0,"wtypeId":0},
{"id":19,"animationId":6,"description":"[Axe] A small axe used for logging trees.","etypeId":1,"traits":[{"code":31,"dataId":1,"value":0},{"code":22,"dataId":0,"value":0}],"iconIndex":99,"name":"Hand Axe","note":"","params":[0,0,10,0,0,0,0,0],"price":480,"wtypeId":4},
{"id":20,"animationId":6,"description":"[Axe] A double-edged axe made for battle.","etypeId":1,"traits":[{"code":31,"dataId":1,"value":0},{"code":22,"dataId":0,"value":0}],"iconIndex":99,"name":"Battle Axe","note":"","params":[0,0,18,0,0,0,0,0],"price":980,"wtypeId":4},
{"id":21,"animationId":6,"description":"[Axe] A battle axe with a crescent-shaped blade.","etypeId":1,"traits":[{"code":31,"dataId":1,"value":0},{"code":22,"dataId":0,"value":0}],"iconIndex":99,"name":"Bardiche","note":"","params":[0,0,25,0,0,0,0,0],"price":2180,"wtypeId":4},
{"id":22,"animationId":6,"description":"[Axe] A battle axe forged with mithril.","etypeId":1,"traits":[{"code":31,"dataId":1,"value":0},{"code":22,"dataId":0,"value":0}],"iconIndex":99,"name":"Mithril Axe","note":"","params":[0,0,32,0,0,0,0,0],"price":4500,"wtypeId":4},
{"id":23,"animationId":6,"description":"[Axe] A battle axe forged from the fangs of a dragon.","etypeId":1,"traits":[{"code":31,"dataId":1,"value":0},{"code":22,"dataId":0,"value":0}],"iconIndex":99,"name":"Dragon Axe","note":"","params":[0,0,45,0,0,0,0,0],"price":9600,"wtypeId":4},
{"id":24,"animationId":0,"description":"","etypeId":1,"traits":[{"code":31,"dataId":1,"value":0},{"code":22,"dataId":0,"value":0}],"iconIndex":0,"name":"","note":"","params":[0,0,0,0,0,0,0,0],"price":0,"wtypeId":0},
{"id":25,"animationId":11,"description":"[Spear] A short spear specialized for thrusting.","etypeId":1,"traits":[{"code":31,"dataId":1,"value":0},{"code":22,"dataId":0,"value":0}],"iconIndex":107,"name":"Short Spear","note":"","params":[0,0,6,0,0,0,0,0],"price":320,"wtypeId":12},
{"id":26,"animationId":11,"description":"[Spear] A spear with the longest handle possible.","etypeId":1,"traits":[{"code":31,"dataId":1,"value":0},{"code":22,"dataId":0,"value":0}],"iconIndex":107,"name":"Long Spear","note":"","params":[0,0,12,0,0,0,0,0],"price":890,"wtypeId":12},
{"id":27,"animationId":11,"description":"[Spear] A spear with an axe-head at its tip.","etypeId":1,"traits":[{"code":31,"dataId":1,"value":0},{"code":22,"dataId":0,"value":0}],"iconIndex":107,"name":"Halberd","note":"","params":[0,0,18,0,0,0,0,0],"price":1760,"wtypeId":12},
{"id":28,"animationId":11,"description":"[Spear] A spear forged with mithril.","etypeId":1,"traits":[{"code":31,"dataId":1,"value":0},{"code":22,"dataId":0,"value":0}],"iconIndex":107,"name":"Mithril Spear","note":"","params":[0,0,24,0,0,0,0,0],"price":3420,"wtypeId":12},
{"id":29,"animationId":11,"description":"[Spear] A spear forged from the fangs of a dragon.","etypeId":1,"traits":[{"code":31,"dataId":1,"value":0},{"code":22,"dataId":0,"value":0}],"iconIndex":107,"name":"Dragon Spear","note":"","params":[0,0,32,0,0,0,0,0],"price":5980,"wtypeId":12},
{"id":30,"animationId":0,"description":"","etypeId":1,"traits":[{"code":31,"dataId":1,"value":0},{"code":22,"dataId":0,"value":0}],"iconIndex":0,"name":"","note":"","params":[0,0,0,0,0,0,0,0],"price":0,"wtypeId":0},
{"id":31,"animationId":1,"description":"[Glove] A battle glove with spikes attached to its\nknuckles.","etypeId":1,"traits":[{"code":31,"dataId":1,"value":0},{"code":22,"dataId":0,"value":0},{"code":54,"dataId":2,"value":1},{"code":34,"dataId":0,"value":1}],"iconIndex":106,"name":"Cestus","note":"","params":[0,0,5,5,0,0,0,0],"price":360,"wtypeId":11},
{"id":32,"animationId":16,"description":"[Claw] A combat weapon with 4 short claws attached.","etypeId":1,"traits":[{"code":31,"dataId":1,"value":0},{"code":22,"dataId":0,"value":0},{"code":54,"dataId":2,"value":1},{"code":34,"dataId":0,"value":1}],"iconIndex":105,"name":"Bagh Naka","note":"","params":[0,0,12,8,0,0,0,0],"price":980,"wtypeId":10},
{"id":33,"animationId":16,"description":"[Claw] A combat weapon with iron talons attached.","etypeId":1,"traits":[{"code":31,"dataId":1,"value":0},{"code":22,"dataId":0,"value":0},{"code":54,"dataId":2,"value":1},{"code":34,"dataId":0,"value":1}],"iconIndex":105,"name":"Iron Claw","note":"","params":[0,0,20,15,0,0,0,0],"price":1560,"wtypeId":10},
{"id":34,"animationId":16,"description":"[Claw] A combat weapon with mithril talons attached.","etypeId":1,"traits":[{"code":31,"dataId":1,"value":0},{"code":22,"dataId":0,"value":0},{"code":54,"dataId":2,"value":1},{"code":34,"dataId":0,"value":1}],"iconIndex":105,"name":"Mithril Claw","note":"","params":[0,0,25,18,0,0,0,0],"price":3480,"wtypeId":10},
{"id":35,"animationId":16,"description":"[Claw] A combat weapon with dragon talons attached.","etypeId":1,"traits":[{"code":31,"dataId":1,"value":0},{"code":22,"dataId":0,"value":0},{"code":54,"dataId":2,"value":1},{"code":34,"dataId":0,"value":1}],"iconIndex":105,"name":"Dragon Claw","note":"","params":[0,0,32,21,0,0,0,0],"price":6890,"wtypeId":10},
{"id":36,"animationId":0,"description":"","etypeId":1,"traits":[{"code":31,"dataId":1,"value":0},{"code":22,"dataId":0,"value":0}],"iconIndex":0,"name":"","note":"","params":[0,0,0,0,0,0,0,0],"price":0,"wtypeId":0},
{"id":37,"animationId":11,"description":"[Bow] A short bow made for hunting.","etypeId":1,"traits":[{"code":31,"dataId":1,"value":0},{"code":22,"dataId":0,"value":0}],"iconIndex":102,"name":"Short Bow","note":"","params":[0,0,7,0,0,0,0,0],"price":310,"wtypeId":7},
{"id":38,"animationId":11,"description":"[Bow] A long bow for battle with superior power.","etypeId":1,"traits":[{"code":31,"dataId":1,"value":0},{"code":22,"dataId":0,"value":0}],"iconIndex":102,"name":"Long Bow","note":"","params":[0,0,12,0,0,0,0,0],"price":780,"wtypeId":7},
{"id":39,"animationId":11,"description":"[Bow] A crossbow that shoots arrows with powerful\nsprings.","etypeId":1,"traits":[{"code":31,"dataId":1,"value":0},{"code":22,"dataId":0,"value":0}],"iconIndex":103,"name":"Crossbow","note":"","params":[0,0,18,0,0,0,0,0],"price":1860,"wtypeId":8},
{"id":40,"animationId":11,"description":"[Bow] A crossbow that shoots mithril arrows with\npowerful springs.","etypeId":1,"traits":[{"code":31,"dataId":1,"value":0},{"code":22,"dataId":0,"value":0}],"iconIndex":103,"name":"Mithril Bow","note":"","params":[0,0,23,0,0,0,0,0],"price":3260,"wtypeId":8},
{"id":41,"animationId":11,"description":"[Bow] A long bow for battle made with dragon’s\nwhiskers.","etypeId":1,"traits":[{"code":31,"dataId":1,"value":0},{"code":22,"dataId":0,"value":0}],"iconIndex":102,"name":"Dragon Bow","note":"","params":[0,0,28,0,0,0,0,0],"price":5980,"wtypeId":7},
{"id":42,"animationId":0,"description":"","etypeId":1,"traits":[{"code":31,"dataId":1,"value":0},{"code":22,"dataId":0,"value":0}],"iconIndex":0,"name":"","note":"","params":[0,0,0,0,0,0,0,0],"price":0,"wtypeId":0},
{"id":43,"animationId":6,"description":"[Dagger] A knife used for day-to-day tasks.","etypeId":1,"traits":[{"code":31,"dataId":1,"value":0},{"code":22,"dataId":0,"value":0}],"iconIndex":96,"name":"Knife","note":"","params":[0,0,5,0,0,0,0,0],"price":280,"wtypeId":1},
{"id":44,"animationId":6,"description":"[Dagger] A short blade used in close combat.","etypeId":1,"traits":[{"code":31,"dataId":1,"value":0},{"code":22,"dataId":0,"value":0}],"iconIndex":96,"name":"Daggar","note":"","params":[0,0,9,0,0,0,0,0],"price":690,"wtypeId":1},
{"id":45,"animationId":6,"description":"[Dagger] A dagger with a thicker, sturdier blade.","etypeId":1,"traits":[{"code":31,"dataId":1,"value":0},{"code":22,"dataId":0,"value":0}],"iconIndex":96,"name":"Machete","note":"","params":[0,0,12,0,0,0,0,0],"price":1280,"wtypeId":1},
{"id":46,"animationId":6,"description":"[Dagger] A dagger forged with mithril.","etypeId":1,"traits":[{"code":31,"dataId":1,"value":0},{"code":22,"dataId":0,"value":0}],"iconIndex":96,"name":"Mithril Daggar","note":"","params":[0,0,18,0,0,0,0,0],"price":2930,"wtypeId":1},
{"id":47,"animationId":6,"description":"[Dagger] A dagger forged from the fangs of a dragon.","etypeId":1,"traits":[{"code":31,"dataId":1,"value":0},{"code":22,"dataId":0,"value":0}],"iconIndex":96,"name":"Dragon Daggar","note":"","params":[0,0,23,0,0,0,0,0],"price":5820,"wtypeId":1},
{"id":48,"animationId":0,"description":"","etypeId":1,"traits":[{"code":31,"dataId":1,"value":0},{"code":22,"dataId":0,"value":0}],"iconIndex":0,"name":"","note":"","params":[0,0,0,0,0,0,0,0],"price":0,"wtypeId":0},
{"id":49,"animationId":0,"description":"","etypeId":1,"traits":[{"code":31,"dataId":1,"value":0},{"code":22,"dataId":0,"value":0}],"iconIndex":0,"name":"","note":"","params":[0,0,0,0,0,0,0,0],"price":0,"wtypeId":0},
{"id":50,"animationId":0,"description":"Machado de hastes Longas","etypeId":1,"traits":[],"iconIndex":475,"name":"---- Langøx","note":"","params":[0,0,0,0,0,0,0,0],"price":0,"wtypeId":0},
{"id":51,"animationId":1,"description":"[Langøx] Um machado imponente, batizado em homenagem ao lendário chifre de Gjallar, símbolo de eventos mitológicos. Sua lâmina afiada e longa promete cortar através de desafios como o próprio som do chifre que o inspirou.","etypeId":1,"traits":[{"code":31,"dataId":1,"value":0},{"code":22,"dataId":0,"value":0}],"iconIndex":739,"name":"Gjallarøx","note":"","params":[0,0,8,0,0,0,4,2],"price":80,"wtypeId":13},
{"id":52,"animationId":1,"description":"[Langøx] Um machado robusto, gravado com runas que invocam a proteção de Fjörgardr, evocando a sensação de segurança e resistência. Ideal para os guerreiros que buscam um aliado confiável em batalha.","etypeId":1,"traits":[{"code":31,"dataId":1,"value":0},{"code":22,"dataId":0,"value":0}],"iconIndex":739,"name":"Fjörgardrøx","note":"","params":[2,0,12,2,0,2,6,3],"price":150,"wtypeId":13},
{"id":53,"animationId":2,"description":"[Langøx] Um machado adornado com detalhes que lembram o lendário lobo Sköll, símbolo do sol. A promessa de sua lâmina é tão feroz quanto a busca incansável do lobo pelo astro dourado.","etypeId":1,"traits":[{"code":31,"dataId":1,"value":0},{"code":22,"dataId":0,"value":0}],"iconIndex":419,"name":"Skölløx","note":"","params":[5,0,27,0,0,0,13,7],"price":400,"wtypeId":13},
{"id":54,"animationId":1,"description":"[Langøx] Um machado envolto em chamas, refletindo o significado de \"Eldbrand\" - fogo ardente. Esta arma inflama a batalha, transformando-se em uma extensão das forças do fogo.","etypeId":1,"traits":[{"code":31,"dataId":1,"value":0},{"code":22,"dataId":0,"value":0}],"iconIndex":739,"name":"Eldbrandøx","note":"","params":[3,0,15,0,0,0,7,4],"price":175,"wtypeId":13},
{"id":55,"animationId":1,"description":"[Langøx] Um machado que, além de sua imponente lâmina, exibe um escudo incorporado ao cabo. Uma escolha estratégica para aqueles que valorizam tanto a defesa quanto o ataque.","etypeId":1,"traits":[{"code":31,"dataId":1,"value":0},{"code":22,"dataId":0,"value":0}],"iconIndex":739,"name":"Skjoldbrøx","note":"","params":[3,0,18,9,0,9,9,5],"price":200,"wtypeId":13},
{"id":56,"animationId":2,"description":"[Langøx] Um machado ornamentado com motivos de corvos, honrando os mensageiros da mitologia nórdica. Dizem que este machado traz o olhar atento dos corvos para os seus portadores.","etypeId":1,"traits":[{"code":31,"dataId":1,"value":0},{"code":22,"dataId":0,"value":0}],"iconIndex":419,"name":"Hrafnskjærøx","note":"","params":[6,0,30,0,0,0,15,7],"price":475,"wtypeId":13},
{"id":57,"animationId":2,"description":"[Langøx] Um machado que carrega as marcas da linhagem, lembrando a importância da família e da herança. Cada golpe desse machado é uma extensão da história que seus portadores carregam consigo.","etypeId":1,"traits":[{"code":31,"dataId":1,"value":0},{"code":22,"dataId":0,"value":0}],"iconIndex":419,"name":"Ættartvíøx","note":"","params":[7,0,35,0,0,0,18,9],"price":555,"wtypeId":13},
{"id":58,"animationId":1,"description":"[Langøx] Um machado esculpido com detalhes que evocam a frieza da neve. Seu toque gélido se reflete nas batalhas, congelando a resistência dos inimigos.","etypeId":1,"traits":[{"code":31,"dataId":1,"value":0},{"code":22,"dataId":0,"value":0}],"iconIndex":739,"name":"Snærøx","note":"","params":[4,0,21,4,0,4,11,6],"price":220,"wtypeId":13},
{"id":59,"animationId":2,"description":"[Langøx] Um machado que presta homenagem ao titã primordial Ymir. Seu rugido nas batalhas é como o tumulto do início dos tempos, ressoando poder e força ancestral.","etypeId":1,"traits":[{"code":31,"dataId":1,"value":0},{"code":22,"dataId":0,"value":0}],"iconIndex":419,"name":"Ymirsgnýrøx","note":"","params":[10,0,45,0,0,0,23,12],"price":900,"wtypeId":13},
{"id":60,"animationId":0,"description":"Varinha mágica, encantada com magia nórdica.","etypeId":1,"traits":[],"iconIndex":0,"name":"---- Galdrastafur","note":"","params":[0,0,0,0,0,0,0,0],"price":0,"wtypeId":0},
{"id":61,"animationId":1,"description":"[Galdrastafur] Uma varinha esculpida com o símbolo mágico da sorte, Hamingja Galdrastafur. Ao empunhá-la, os portadores podem influenciar sutilmente o destino a seu favor, trazendo boa sorte em suas jornadas.","etypeId":1,"traits":[{"code":31,"dataId":1,"value":0},{"code":22,"dataId":0,"value":0}],"iconIndex":741,"name":"Hamingja","note":"","params":[0,4,0,0,8,0,2,4],"price":80,"wtypeId":14},
{"id":62,"animationId":1,"description":"[Galdrastafur] Uma varinha adornada com o símbolo sagrado Heilagar Galdrastafur. Ao canalizar seus poderes, os usuários invocam uma proteção divina que os resguarda contra forças malignas.","etypeId":1,"traits":[{"code":31,"dataId":1,"value":0},{"code":22,"dataId":0,"value":0}],"iconIndex":741,"name":"Heilagar","note":"","params":[0,6,0,2,12,2,3,6],"price":150,"wtypeId":14},
{"id":63,"animationId":2,"description":"[Galdrastafur] Uma varinha entalhada com o símbolo da coragem, Þroski Galdrastafur. Aqueles que a empunham encontram a força interior para enfrentar desafios com bravura.","etypeId":1,"traits":[{"code":31,"dataId":1,"value":0},{"code":22,"dataId":0,"value":0}],"iconIndex":421,"name":"Þroski","note":"","params":[7,13,0,0,27,0,7,13],"price":400,"wtypeId":14},
{"id":64,"animationId":1,"description":"[Galdrastafur] Uma varinha encantada com o símbolo de cura, Heil Galdrastafur. Seu toque restaurador e curativo traz alívio aos feridos e doentes.","etypeId":1,"traits":[{"code":31,"dataId":1,"value":0},{"code":22,"dataId":0,"value":0}],"iconIndex":741,"name":"Heil","note":"","params":[0,7,0,0,15,0,4,7],"price":175,"wtypeId":14},
{"id":65,"animationId":1,"description":"[Galdrastafur] Uma varinha gravada com o símbolo protetor, Andlit Galdrastafur. Seu poder cria uma barreira mágica, guardando seu portador contra ameaças e malevolências.","etypeId":1,"traits":[{"code":31,"dataId":1,"value":0},{"code":22,"dataId":0,"value":0}],"iconIndex":741,"name":"Andlit","note":"","params":[0,9,0,0,18,0,5,9],"price":200,"wtypeId":14},
{"id":66,"animationId":2,"description":"[Galdrastafur] Uma varinha adornada com o símbolo da sabedoria, Visdomr Galdrastafur. Seus usuários são guiados por insights profundos e compreensão ampliada.","etypeId":1,"traits":[{"code":31,"dataId":1,"value":0},{"code":22,"dataId":0,"value":0}],"iconIndex":421,"name":"Visdomr","note":"","params":[12,23,0,0,45,0,12,23],"price":900,"wtypeId":14},
{"id":67,"animationId":1,"description":"[Galdrastafur] Uma varinha esculpida com o símbolo do amor, Ást Galdrastafur. Ao ser empunhada, ela emana energias que promovem a harmonia e a união.\n","etypeId":1,"traits":[{"code":31,"dataId":1,"value":0},{"code":22,"dataId":0,"value":0}],"iconIndex":741,"name":"Ást","note":"","params":[0,11,0,0,21,0,6,11],"price":220,"wtypeId":14},
{"id":68,"animationId":2,"description":"[Galdrastafur] Uma varinha ornamentada com o símbolo da perícia, Fjölkunnigr Galdrastafur. Seu toque aprimora as habilidades do portador em suas áreas de expertise.","etypeId":1,"traits":[{"code":31,"dataId":1,"value":0},{"code":22,"dataId":0,"value":0}],"iconIndex":421,"name":"Fjölkunnigr","note":"","params":[9,18,0,0,35,0,9,18],"price":555,"wtypeId":14},
{"id":69,"animationId":2,"description":"[Galdrastafur] Uma varinha encantada com o símbolo dos sonhos, Draumr Galdrastafur. Ao ser agitada, ela se conecta aos reinos oníricos, trazendo visões reveladoras e insights durante o sono.","etypeId":1,"traits":[{"code":31,"dataId":1,"value":0},{"code":22,"dataId":0,"value":0}],"iconIndex":421,"name":"Draumr","note":"","params":[7,15,0,0,30,0,7,15],"price":475,"wtypeId":14},
{"id":70,"animationId":0,"description":"[Galdrastafur]","etypeId":1,"traits":[{"code":31,"dataId":1,"value":0},{"code":22,"dataId":0,"value":0}],"iconIndex":0,"name":"","note":"","params":[0,0,0,0,0,0,0,0],"price":0,"wtypeId":14}
]